<mujoco model="target">
  <compiler meshdir="assets" texturedir="assets" autolimits="true"/>
  <default>
    <default class="visual">
      <geom group="2" type="mesh" contype="0" conaffinity="0"/>
    </default>
    <default class="collision">
      <geom group="3" type="mesh"/>
    </default>
  </default>
  <asset>
    <material name="236,241,239" specular="1.0" shininess="1.0" rgba="0.925490 0.945098 0.937255 0.220000"/>
    <material name="197,194,148" specular="1.0" shininess="1.0" rgba="0.772549 0.760784 0.580392 1.000000"/>
    <mesh file="object_0.obj"/>
    <mesh file="object_1.obj"/>
  </asset>
  <worldbody>
    <body name="object">
      <geom mesh="object_0" material="197,194,148" class="visual"/>
      <geom mesh="object_1" material="236,241,239" class="visual"/>
      <geom mesh="object_0" class="collision"/>
      <geom mesh="object_1" class="collision"/>
    </body>
  </worldbody>
</mujoco>
